poetry_plugin_package_info/__init__.py
poetry_plugin_package_info/_zipfile.py
poetry_plugin_package_info/formatters/__init__.py
poetry_plugin_package_info/formatters/black.py
poetry_plugin_package_info/generators/__init__.py
poetry_plugin_package_info/generators/git.py
poetry_plugin_package_info/generators/project.py
poetry_plugin_package_info/package_info.py
poetry_plugin_package_info/plugin.py
poetry_plugin_package_info-1.0.0.dist-info/LICENSE
poetry_plugin_package_info-1.0.0.dist-info/METADATA
poetry_plugin_package_info-1.0.0.dist-info/WHEEL
poetry_plugin_package_info-1.0.0.dist-info/entry_points.txt
poetry_plugin_package_info-1.0.0.dist-info/RECORD